[
    {
        "word": "extra",
        "ipa": "ˈɛkstrə",
        "meaning": "thêm"
    },
    {
        "word": "half-price",
        "ipa": "ˈhɑːfˈpraɪs",
        "meaning": "một nửa giá"
    },
    {
        "word": "small",
        "ipa": "smɔːl",
        "meaning": "nhỏ"
    },
    {
        "word": "rich",
        "ipa": "rɪʧ",
        "meaning": "giàu có"
    },
    {
        "word": "online",
        "ipa": "ˈɒnˌlaɪn",
        "meaning": "Trực tuyến"
    },
    {
        "word": "cloudy",
        "ipa": "ˈklaʊdi",
        "meaning": "Nhiều mây"
    },
    {
        "word": "plastic",
        "ipa": "ˈplæstɪk",
        "meaning": "nhựa"
    },
    {
        "word": "hot",
        "ipa": "hɒt",
        "meaning": "nóng bức"
    },
    {
        "word": "strange",
        "ipa": "streɪnʤ",
        "meaning": "lạ"
    },
    {
        "word": "dry",
        "ipa": "draɪ",
        "meaning": "khô"
    },
    {
        "word": "busy",
        "ipa": "ˈbɪzi",
        "meaning": "bận"
    },
    {
        "word": "good",
        "ipa": "gʊd",
        "meaning": "tốt"
    },
    {
        "word": "slow",
        "ipa": "sləʊ",
        "meaning": "chậm"
    },
    {
        "word": "poor",
        "ipa": "pʊə",
        "meaning": "nghèo"
    },
    {
        "word": "broken",
        "ipa": "ˈbrəʊkən",
        "meaning": "bị hỏng"
    },
    {
        "word": "thirsty",
        "ipa": "ˈθɜːsti",
        "meaning": "khát nước"
    },
    {
        "word": "excellent",
        "ipa": "ˈɛksələnt",
        "meaning": "thông minh"
    },
    {
        "word": "singular",
        "ipa": "ˈsɪŋgjʊlə",
        "meaning": "số ít"
    },
    {
        "word": "free",
        "ipa": "friː",
        "meaning": "miễn phí"
    },
    {
        "word": "single",
        "ipa": "ˈsɪŋgl",
        "meaning": "Độc thân"
    },
    {
        "word": "hungry",
        "ipa": "ˈhʌŋgri",
        "meaning": "đói bụng"
    },
    {
        "word": "double",
        "ipa": "ˈdʌbl",
        "meaning": "gấp đôi"
    },
    {
        "word": "full",
        "ipa": "fʊl",
        "meaning": "đầy"
    },
    {
        "word": "dirty",
        "ipa": "ˈdɜːti",
        "meaning": "dơ bẩn"
    },
    {
        "word": "fun",
        "ipa": "fʌn",
        "meaning": "vui vẻ"
    },
    {
        "word": "deep",
        "ipa": "diːp",
        "meaning": "sâu"
    },
    {
        "word": "simple",
        "ipa": "ˈsɪmpl",
        "meaning": "đơn giản"
    },
    {
        "word": "white",
        "ipa": "waɪt",
        "meaning": "trắng"
    },
    {
        "word": "close",
        "ipa": "kləʊs",
        "meaning": "đóng"
    },
    {
        "word": "dark",
        "ipa": "dɑːk",
        "meaning": "tối"
    },
    {
        "word": "short",
        "ipa": "ʃɔːt",
        "meaning": "ngắn"
    },
    {
        "word": "well-known",
        "ipa": "wɛl-nəʊn",
        "meaning": "nổi tiếng"
    },
    {
        "word": "healthy",
        "ipa": "ˈhɛlθi",
        "meaning": "khỏe mạnh"
    },
    {
        "word": "mad",
        "ipa": "mæd",
        "meaning": "điên"
    },
    {
        "word": "cream",
        "ipa": "kriːm",
        "meaning": "kem"
    },
    {
        "word": "friendly",
        "ipa": "ˈfrɛndli",
        "meaning": "thân thiện"
    },
    {
        "word": "sweet",
        "ipa": "swiːt",
        "meaning": "ngọt"
    },
    {
        "word": "upset",
        "ipa": "ʌpˈsɛt",
        "meaning": "buồn bã"
    },
    {
        "word": "clear",
        "ipa": "klɪə",
        "meaning": "thông thoáng"
    },
    {
        "word": "purple",
        "ipa": "ˈpɜːpl",
        "meaning": "màu tím"
    },
    {
        "word": "golden",
        "ipa": "ˈgəʊldən",
        "meaning": "vàng"
    },
    {
        "word": "same",
        "ipa": "seɪm",
        "meaning": "tương tự"
    },
    {
        "word": "roast",
        "ipa": "rəʊst",
        "meaning": "nướng"
    },
    {
        "word": "sad",
        "ipa": "sæd",
        "meaning": "buồn"
    },
    {
        "word": "clean",
        "ipa": "kliːn",
        "meaning": "dọn dẹp"
    },
    {
        "word": "pleasant",
        "ipa": "ˈplɛznt",
        "meaning": "hài lòng"
    },
    {
        "word": "OK",
        "ipa": "ˈəʊˈkeɪ",
        "meaning": "đồng ý"
    },
    {
        "word": "safe",
        "ipa": "seɪf",
        "meaning": "an toàn"
    },
    {
        "word": "red",
        "ipa": "rɛd",
        "meaning": "màu đỏ"
    },
    {
        "word": "brown",
        "ipa": "braʊn",
        "meaning": "nâu"
    },
    {
        "word": "pink",
        "ipa": "pɪŋk",
        "meaning": "Hồng"
    },
    {
        "word": "great",
        "ipa": "greɪt",
        "meaning": "tuyệt quá"
    },
    {
        "word": "first",
        "ipa": "fɜːst",
        "meaning": "Đầu tiên"
    },
    {
        "word": "right",
        "ipa": "raɪt",
        "meaning": "đúng"
    },
    {
        "word": "yellow",
        "ipa": "ˈjɛləʊ",
        "meaning": "màu vàng"
    },
    {
        "word": "nice",
        "ipa": "naɪs",
        "meaning": "đẹp"
    },
    {
        "word": "foreign",
        "ipa": "ˈfɒrɪn",
        "meaning": "ngoại quốc"
    },
    {
        "word": "perfect",
        "ipa": "ˈpɜːfɪkt",
        "meaning": "hoàn hảo"
    },
    {
        "word": "cool",
        "ipa": "kuːl",
        "meaning": "mát mẻ"
    },
    {
        "word": "final",
        "ipa": "ˈfaɪnl",
        "meaning": "sau cùng"
    },
    {
        "word": "real",
        "ipa": "rɪəl",
        "meaning": "thực tế"
    },
    {
        "word": "worst",
        "ipa": "wɜːst",
        "meaning": "tệ nhất"
    },
    {
        "word": "kind",
        "ipa": "kaɪnd",
        "meaning": "Tốt bụng"
    },
    {
        "word": "fresh",
        "ipa": "frɛʃ",
        "meaning": "tươi"
    },
    {
        "word": "polite",
        "ipa": "pəˈlaɪt",
        "meaning": "lịch sự"
    },
    {
        "word": "fast",
        "ipa": "fɑːst",
        "meaning": "Nhanh"
    },
    {
        "word": "worse",
        "ipa": "wɜːs",
        "meaning": "tệ hơn"
    },
    {
        "word": "happy",
        "ipa": "ˈhæpi",
        "meaning": "vui mừng"
    },
    {
        "word": "brilliant",
        "ipa": "ˈbrɪljənt",
        "meaning": "xuất sắc"
    },
    {
        "word": "orange",
        "ipa": "ˈɒrɪnʤ",
        "meaning": "trái cam"
    },
    {
        "word": "awesome",
        "ipa": "ˈɔːsəm",
        "meaning": "tuyệt vời"
    },
    {
        "word": "ready",
        "ipa": "ˈrɛdi",
        "meaning": "Sẵn sàng"
    },
    {
        "word": "wide",
        "ipa": "waɪd",
        "meaning": "rộng"
    },
    {
        "word": "bright",
        "ipa": "braɪt",
        "meaning": "sáng"
    },
    {
        "word": "old",
        "ipa": "əʊld",
        "meaning": "cũ"
    },
    {
        "word": "empty",
        "ipa": "ˈɛmpti",
        "meaning": "trống"
    },
    {
        "word": "blue",
        "ipa": "bluː",
        "meaning": "màu xanh da trời"
    },
    {
        "word": "warm",
        "ipa": "wɔːm",
        "meaning": "ấm áp"
    },
    {
        "word": "amazing",
        "ipa": "əˈmeɪzɪŋ",
        "meaning": "kinh ngạc"
    },
    {
        "word": "easy",
        "ipa": "ˈiːzi",
        "meaning": "dễ dàng"
    },
    {
        "word": "whole",
        "ipa": "həʊl",
        "meaning": "toàn bộ"
    },
    {
        "word": "black",
        "ipa": "blæk",
        "meaning": "đen"
    },
    {
        "word": "well",
        "ipa": "wɛl",
        "meaning": "tốt"
    },
    {
        "word": "electric",
        "ipa": "ɪˈlɛktrɪk",
        "meaning": "điện"
    },
    {
        "word": "new",
        "ipa": "njuː",
        "meaning": "Mới"
    },
    {
        "word": "fantastic",
        "ipa": "fænˈtæstɪk",
        "meaning": "tuyệt diệu"
    },
    {
        "word": "east",
        "ipa": "iːst",
        "meaning": "phía đông"
    },
    {
        "word": "quiet",
        "ipa": "ˈkwaɪət",
        "meaning": "Yên tĩnh"
    },
    {
        "word": "glad",
        "ipa": "glæd",
        "meaning": "vui vẻ"
    },
    {
        "word": "big",
        "ipa": "bɪg",
        "meaning": "lớn"
    },
    {
        "word": "sick",
        "ipa": "sɪk",
        "meaning": "đau ốm"
    },
    {
        "word": "careful",
        "ipa": "ˈkeəfʊl",
        "meaning": "cẩn thận"
    },
    {
        "word": "low",
        "ipa": "ləʊ",
        "meaning": "Thấp"
    },
    {
        "word": "early",
        "ipa": "ˈɜːli",
        "meaning": "sớm"
    },
    {
        "word": "thin",
        "ipa": "θɪn",
        "meaning": "gầy"
    },
    {
        "word": "favourite",
        "ipa": "ˈfeɪvərɪt",
        "meaning": "yêu thích"
    },
    {
        "word": "best",
        "ipa": "bɛst",
        "meaning": "tốt"
    },
    {
        "word": "long",
        "ipa": "lɒŋ",
        "meaning": "Dài"
    },
    {
        "word": "difficult",
        "ipa": "ˈdɪfɪkəlt",
        "meaning": "khó khăn"
    },
    {
        "word": "quick",
        "ipa": "kwɪk",
        "meaning": "nhanh chóng"
    },
    {
        "word": "terrible",
        "ipa": "ˈtɛrəbl",
        "meaning": "kinh khủng"
    },
    {
        "word": "crazy",
        "ipa": "ˈkreɪzi",
        "meaning": "khùng"
    },
    {
        "word": "bad",
        "ipa": "bæd",
        "meaning": "xấu"
    },
    {
        "word": "little",
        "ipa": "ˈlɪtl",
        "meaning": "ít"
    },
    {
        "word": "beautiful",
        "ipa": "ˈbjuːtəfʊl",
        "meaning": "xinh đẹp"
    },
    {
        "word": "loud",
        "ipa": "laʊd",
        "meaning": "to tiếng"
    },
    {
        "word": "straight",
        "ipa": "streɪt",
        "meaning": "thẳng"
    },
    {
        "word": "clever",
        "ipa": "ˈklɛvə",
        "meaning": "tài giỏi"
    },
    {
        "word": "light",
        "ipa": "laɪt",
        "meaning": "ánh sáng"
    },
    {
        "word": "correct",
        "ipa": "kəˈrɛkt",
        "meaning": "chính xác"
    },
    {
        "word": "own",
        "ipa": "əʊn",
        "meaning": "sở hữu"
    },
    {
        "word": "special",
        "ipa": "ˈspɛʃəl",
        "meaning": "đặc biệt"
    },
    {
        "word": "afraid",
        "ipa": "əˈfreɪd",
        "meaning": "sợ"
    },
    {
        "word": "ill",
        "ipa": "ɪl",
        "meaning": "tôi sẽ"
    },
    {
        "word": "wonderful",
        "ipa": "ˈwʌndəfʊl",
        "meaning": "Tuyệt vời"
    },
    {
        "word": "dead",
        "ipa": "dɛd",
        "meaning": "đã chết"
    },
    {
        "word": "famous",
        "ipa": "ˈfeɪməs",
        "meaning": "nổi danh"
    },
    {
        "word": "back",
        "ipa": "bæk",
        "meaning": "trở lại"
    },
    {
        "word": "cold",
        "ipa": "kəʊld",
        "meaning": "lạnh"
    },
    {
        "word": "open",
        "ipa": "ˈəʊpən",
        "meaning": "mở"
    },
    {
        "word": "soft",
        "ipa": "sɒft",
        "meaning": "mềm mại"
    },
    {
        "word": "young",
        "ipa": "jʌŋ",
        "meaning": "trẻ"
    },
    {
        "word": "useful",
        "ipa": "ˈjuːsfʊl",
        "meaning": "hữu ích"
    },
    {
        "word": "popular",
        "ipa": "ˈpɒpjʊlə",
        "meaning": "phổ biến"
    },
    {
        "word": "square",
        "ipa": "skweə",
        "meaning": "Quảng trường"
    },
    {
        "word": "angry",
        "ipa": "ˈæŋgri",
        "meaning": "bực bội"
    },
    {
        "word": "fit",
        "ipa": "fɪt",
        "meaning": "Phù hợp"
    },
    {
        "word": "closed",
        "ipa": "kləʊzd",
        "meaning": "đóng cửa"
    },
    {
        "word": "dangerous",
        "ipa": "ˈdeɪnʤrəs",
        "meaning": "nguy hiểm"
    },
    {
        "word": "fried",
        "ipa": "fraɪd",
        "meaning": "chiên"
    },
    {
        "word": "sorry",
        "ipa": "ˈsɒri",
        "meaning": "lấy làm tiếc"
    },
    {
        "word": "left-hand",
        "ipa": "lɛft-hænd",
        "meaning": "tay trái"
    },
    {
        "word": "only",
        "ipa": "ˈəʊnli",
        "meaning": "chỉ có"
    },
    {
        "word": "strong",
        "ipa": "strɒŋ",
        "meaning": "mạnh"
    },
    {
        "word": "fine",
        "ipa": "faɪn",
        "meaning": "khỏe"
    },
    {
        "word": "better",
        "ipa": "ˈbɛtə",
        "meaning": "tốt hơn"
    },
    {
        "word": "married",
        "ipa": "ˈmærɪd",
        "meaning": "cưới nhau"
    },
    {
        "word": "lovely",
        "ipa": "ˈlʌvli",
        "meaning": "đáng yêu"
    },
    {
        "word": "boiled",
        "ipa": "bɔɪld",
        "meaning": "luộc"
    },
    {
        "word": "left",
        "ipa": "lɛft",
        "meaning": "trái"
    },
    {
        "word": "cheap",
        "ipa": "ʧiːp",
        "meaning": "rẻ"
    },
    {
        "word": "advanced",
        "ipa": "ədˈvɑːnst",
        "meaning": "nâng cao"
    },
    {
        "word": "large",
        "ipa": "lɑːʤ",
        "meaning": "lớn"
    },
    {
        "word": "north",
        "ipa": "nɔːθ",
        "meaning": "Bắc"
    },
    {
        "word": "alright",
        "ipa": "ɔːlˈraɪt",
        "meaning": "ổn thỏa"
    },
    {
        "word": "worried",
        "ipa": "ˈwʌrid",
        "meaning": "lo lắng"
    },
    {
        "word": "attractive",
        "ipa": "əˈtræktɪv",
        "meaning": "hấp dẫn"
    },
    {
        "word": "important",
        "ipa": "ɪmˈpɔːtənt",
        "meaning": "quan trọng"
    },
    {
        "word": "indoor",
        "ipa": "ˈɪndɔː",
        "meaning": "trong nhà"
    },
    {
        "word": "next",
        "ipa": "nɛkst",
        "meaning": "kế tiếp"
    },
    {
        "word": "silver",
        "ipa": "ˈsɪlvə",
        "meaning": "bạc"
    },
    {
        "word": "slim",
        "ipa": "slɪm",
        "meaning": "mảnh khảnh"
    },
    {
        "word": "all right",
        "ipa": "ɔːl raɪt",
        "meaning": "được rồi"
    },
    {
        "word": "different",
        "ipa": "ˈdɪfrənt",
        "meaning": "khác nhau"
    },
    {
        "word": "tired",
        "ipa": "ˈtaɪəd",
        "meaning": "mệt mỏi"
    },
    {
        "word": "interesting",
        "ipa": "ˈɪntrɪstɪŋ",
        "meaning": "hấp dẫn"
    },
    {
        "word": "digital",
        "ipa": "ˈdɪʤɪtl",
        "meaning": "kỹ thuật số"
    },
    {
        "word": "horrible",
        "ipa": "ˈhɒrəbl",
        "meaning": "kinh khủng"
    },
    {
        "word": "round",
        "ipa": "raʊnd",
        "meaning": "tròn"
    },
    {
        "word": "surprised",
        "ipa": "səˈpraɪzd",
        "meaning": "ngạc nhiên"
    },
    {
        "word": "heavy",
        "ipa": "ˈhɛvi",
        "meaning": "nặng"
    },
    {
        "word": "alone",
        "ipa": "əˈləʊn",
        "meaning": "một mình"
    },
    {
        "word": "right-hand",
        "ipa": "raɪt-hænd",
        "meaning": "tay phải"
    },
    {
        "word": "pretty",
        "ipa": "ˈprɪti",
        "meaning": "đẹp"
    },
    {
        "word": "pleased",
        "ipa": "pliːzd",
        "meaning": "vừa lòng"
    },
    {
        "word": "exciting",
        "ipa": "ɪkˈsaɪtɪŋ",
        "meaning": "thú vị"
    },
    {
        "word": "national",
        "ipa": "ˈnæʃənl",
        "meaning": "Quốc gia"
    },
    {
        "word": "dear",
        "ipa": "dɪə",
        "meaning": "kính thưa"
    },
    {
        "word": "high",
        "ipa": "haɪ",
        "meaning": "cao"
    },
    {
        "word": "wrong",
        "ipa": "rɒŋ",
        "meaning": "Sai lầm"
    },
    {
        "word": "interested",
        "ipa": "ˈɪntrɪstɪd",
        "meaning": "thú vị"
    },
    {
        "word": "hard",
        "ipa": "hɑːd",
        "meaning": "cứng"
    },
    {
        "word": "adult",
        "ipa": "ˈædʌlt",
        "meaning": "người lớn"
    },
    {
        "word": "magic",
        "ipa": "ˈmæʤɪk",
        "meaning": "ma thuật"
    },
    {
        "word": "boring",
        "ipa": "ˈbɔːrɪŋ",
        "meaning": "nhàm chán"
    },
    {
        "word": "wild",
        "ipa": "waɪld",
        "meaning": "hoang dã"
    },
    {
        "word": "musical",
        "ipa": "ˈmjuːzɪkəl",
        "meaning": "âm nhạc"
    },
    {
        "word": "possible",
        "ipa": "ˈpɒsəbl",
        "meaning": "khả thi"
    },
    {
        "word": "noisy",
        "ipa": "ˈnɔɪzi",
        "meaning": "ồn ào"
    },
    {
        "word": "lost",
        "ipa": "lɒst",
        "meaning": "mất đi"
    },
    {
        "word": "good-looking",
        "ipa": "ˈgʊdˈlʊkɪŋ",
        "meaning": "ưa nhìn"
    },
    {
        "word": "wet",
        "ipa": "wɛt",
        "meaning": "ướt"
    },
    {
        "word": "available",
        "ipa": "əˈveɪləbl",
        "meaning": "có sẵn"
    },
    {
        "word": "fat",
        "ipa": "fæt",
        "meaning": "mập"
    },
    {
        "word": "further",
        "ipa": "ˈfɜːðə",
        "meaning": "thêm nữa"
    },
    {
        "word": "modern",
        "ipa": "ˈmɒdən",
        "meaning": "hiện đại"
    },
    {
        "word": "wooden",
        "ipa": "ˈwʊdn",
        "meaning": "gỗ"
    },
    {
        "word": "excited",
        "ipa": "ɪkˈsaɪtɪd",
        "meaning": "bị kích thích"
    },
    {
        "word": "lucky",
        "ipa": "ˈlʌki",
        "meaning": "may mắn"
    },
    {
        "word": "west",
        "ipa": "wɛst",
        "meaning": "hướng Tây"
    },
    {
        "word": "comfortable",
        "ipa": "ˈkʌmf(ə)təbl",
        "meaning": "Thoải mái"
    },
    {
        "word": "fair",
        "ipa": "feə",
        "meaning": "hội chợ"
    },
    {
        "word": "dressed",
        "ipa": "drɛst",
        "meaning": "mặc quần áo"
    },
    {
        "word": "bored",
        "ipa": "bɔːd",
        "meaning": "chán"
    },
    {
        "word": "grey",
        "ipa": "greɪ",
        "meaning": "màu xám"
    },
    {
        "word": true,
        "ipa": "truː",
        "meaning": "THẬT"
    },
    {
        "word": "unhappy",
        "ipa": "ʌnˈhæpi",
        "meaning": "không vui"
    },
    {
        "word": "blonde",
        "ipa": "blɒnd",
        "meaning": "vàng"
    },
    {
        "word": "crowded",
        "ipa": "ˈkraʊdɪd",
        "meaning": "Đông người"
    },
    {
        "word": "grilled",
        "ipa": "grɪld",
        "meaning": "nướng"
    },
    {
        "word": "green",
        "ipa": "griːn",
        "meaning": "màu xanh lá"
    },
    {
        "word": "various",
        "ipa": "ˈveərɪəs",
        "meaning": "đa dạng"
    },
    {
        "word": "latest",
        "ipa": "ˈleɪtɪst",
        "meaning": "muộn nhất"
    },
    {
        "word": "lazy",
        "ipa": "ˈleɪzi",
        "meaning": "lười biếng"
    },
    {
        "word": "weekly",
        "ipa": "ˈwiːkli",
        "meaning": "hàng tuần"
    },
    {
        "word": "late",
        "ipa": "leɪt",
        "meaning": "muộn"
    },
    {
        "word": "tidy",
        "ipa": "ˈtaɪdi",
        "meaning": "gọn gàng"
    },
    {
        "word": "funny",
        "ipa": "ˈfʌni",
        "meaning": "buồn cười"
    },
    {
        "word": "daily",
        "ipa": "ˈdeɪli",
        "meaning": "hằng ngày"
    },
    {
        "word": "tall",
        "ipa": "tɔːl",
        "meaning": "cao"
    },
    {
        "word": "aged",
        "ipa": "eɪʤd",
        "meaning": "tuổi"
    },
    {
        "word": "normal",
        "ipa": "ˈnɔːməl",
        "meaning": "bình thường"
    },
    {
        "word": "windy",
        "ipa": "ˈwɪndi",
        "meaning": "gió"
    },
    {
        "word": "negative",
        "ipa": "ˈnɛgətɪv",
        "meaning": "tiêu cực"
    },
    {
        "word": "last",
        "ipa": "lɑːst",
        "meaning": "Cuối cùng"
    },
    {
        "word": "sunny",
        "ipa": "ˈsʌni",
        "meaning": "nắng"
    },
    {
        "word": "expensive",
        "ipa": "ɪksˈpɛnsɪv",
        "meaning": "đắt"
    },
    {
        "word": "unusual",
        "ipa": "ʌnˈjuːʒʊəl",
        "meaning": "bất thường"
    },
    {
        "word": "gold",
        "ipa": "gəʊld",
        "meaning": "vàng"
    },
    {
        "word": "sure",
        "ipa": "ʃʊə",
        "meaning": "chắc chắn rồi"
    },
    {
        "word": "international",
        "ipa": "ˌɪntə(ː)ˈnæʃənl",
        "meaning": "Quốc tế"
    },
    {
        "word": "south",
        "ipa": "saʊθ",
        "meaning": "miền Nam"
    },
    {
        "word": "foggy",
        "ipa": "ˈfɒgi",
        "meaning": "sương mù"
    },
    {
        "word": "missing",
        "ipa": "ˈmɪsɪŋ",
        "meaning": "còn thiếu"
    }
]